sgw_tools/__init__.py
sgw_tools/approximations.py
sgw_tools/filters.py
sgw_tools/graph.py
sgw_tools/graphs.py
sgw_tools/util.py
sgw_torch/__init__.py
sgw_torch/layers.py
tests/__init__.py
tests/test_biggraph.py
tests/test_sgw.py
tests/test_torch.py
tests/test_util.py
sgw_tools-3.1.1.dist-info/LICENSE
sgw_tools-3.1.1.dist-info/METADATA
sgw_tools-3.1.1.dist-info/WHEEL
sgw_tools-3.1.1.dist-info/top_level.txt
sgw_tools-3.1.1.dist-info/RECORD
