Metadata-Version: 2.1
Name: sgw_tools
Version: 3.1.1
Summary: Spectral graph wavelet tools
Home-page: https://github.com/pulquero/sgw
Author: Mark Hale
License: MIT
Classifier: Programming Language :: Python :: 3
Classifier: License :: OSI Approved :: MIT License
Classifier: Operating System :: OS Independent
Requires-Python: >=3.8
License-File: LICENSE
